infinigen/__init__.py
infinigen/launch_blender.py
infinigen/OcMesher/__init__.py
infinigen/OcMesher/demo.py
infinigen/OcMesher/requirements.txt
infinigen/OcMesher/ocmesher/__init__.py
infinigen/OcMesher/ocmesher/core.py
infinigen/OcMesher/ocmesher/utils/__init__.py
infinigen/OcMesher/ocmesher/utils/interface.py
infinigen/OcMesher/ocmesher/utils/timer.py
infinigen/assets/__init__.py
infinigen/assets/colors.py
infinigen/assets/composition/material_assignments.py
infinigen/assets/fluid/__init__.py
infinigen/assets/fluid/asset_cache.py
infinigen/assets/fluid/bounding_box.py
infinigen/assets/fluid/cached_factory_wrappers.py
infinigen/assets/fluid/duplication_geomod.py
infinigen/assets/fluid/flip_fluid.py
infinigen/assets/fluid/flip_init.py
infinigen/assets/fluid/fluid.py
infinigen/assets/fluid/fluid_scenecomp_additions.py
infinigen/assets/fluid/generate.py
infinigen/assets/fluid/liquid_particle_material.py
infinigen/assets/fluid/run_asset_cache.py
infinigen/assets/fluid/run_tests.py
infinigen/assets/fluid/unit_tests.py
infinigen/assets/fonts/Chakra_Petch/OFL.txt
infinigen/assets/fonts/Dancing_Script/OFL.txt
infinigen/assets/fonts/Dancing_Script/README.txt
infinigen/assets/fonts/Ga_Maamli/OFL.txt
infinigen/assets/fonts/Maname/OFL.txt
infinigen/assets/fonts/Merriweather/OFL.txt
infinigen/assets/fonts/Montserrat/OFL.txt
infinigen/assets/fonts/Montserrat/README.txt
infinigen/assets/fonts/Open_Sans/OFL.txt
infinigen/assets/fonts/Open_Sans/README.txt
infinigen/assets/fonts/Oswald/OFL.txt
infinigen/assets/fonts/Oswald/README.txt
infinigen/assets/fonts/Pacifico/OFL.txt
infinigen/assets/fonts/Playfair_Display/OFL.txt
infinigen/assets/fonts/Playfair_Display/README.txt
infinigen/assets/lighting/__init__.py
infinigen/assets/lighting/caustics_lamp.py
infinigen/assets/lighting/hdri_lighting.py
infinigen/assets/lighting/holdout_lighting.py
infinigen/assets/lighting/indoor_lights.py
infinigen/assets/lighting/sky_lighting.py
infinigen/assets/lighting/three_point_lighting.py
infinigen-1.15.5.dist-info/METADATA
infinigen-1.15.5.dist-info/WHEEL
infinigen-1.15.5.dist-info/top_level.txt
infinigen-1.15.5.dist-info/RECORD
