Metadata-Version: 2.4
Name: infinigen
Version: 1.15.5
Summary: Infinite Photorealistic Worlds using Procedural Generation
License: BSD-3-Clause
Keywords: computer vision,data generation,procedural
Classifier: Programming Language :: Python :: 3
Requires-Python: ==3.11.*
Requires-Dist: bpy==4.2.0
Requires-Dist: coacd
Requires-Dist: gin_config>=0.5.0
Requires-Dist: imageio<2.32.0
Requires-Dist: matplotlib
Requires-Dist: networkx
Requires-Dist: numpy<2
Requires-Dist: opencv-python<4.9.0
Requires-Dist: pandas
Requires-Dist: psutil
Requires-Dist: scikit-image<0.20.0
Requires-Dist: scikit-learn<1.4.0
Requires-Dist: scipy
Requires-Dist: shapely<=2.0.5
Requires-Dist: tqdm
Requires-Dist: trimesh<3.23.0
Requires-Dist: OpenEXR
Requires-Dist: submitit
Requires-Dist: geomdl
Requires-Dist: python-fcl
Requires-Dist: rtree
Provides-Extra: terrain
Requires-Dist: landlab==2.6.0; extra == "terrain"
Requires-Dist: pyrender<0.2.0; extra == "terrain"
Requires-Dist: setuptools; extra == "terrain"
Provides-Extra: vis
Requires-Dist: einops; extra == "vis"
Requires-Dist: flow_vis; extra == "vis"
Requires-Dist: numba; extra == "vis"
Requires-Dist: pyglet<2; extra == "vis"
Provides-Extra: dev
Requires-Dist: pytest; extra == "dev"
Requires-Dist: pytest-cov; extra == "dev"
Requires-Dist: pytest-xdist; extra == "dev"
Requires-Dist: pytest-timeout; extra == "dev"
Requires-Dist: pytype; extra == "dev"
Requires-Dist: ruff; extra == "dev"
Requires-Dist: isort; extra == "dev"
Requires-Dist: tabulate; extra == "dev"
Requires-Dist: rapidfuzz; extra == "dev"
Requires-Dist: pre-commit; extra == "dev"
Provides-Extra: wandb
Requires-Dist: wandb; extra == "wandb"
